xlranker/__init__.py
xlranker/cli.py
xlranker/config.py
xlranker/lib.py
xlranker/pipeline.py
xlranker/report.py
xlranker/selection.py
xlranker/status.py
xlranker/bio/__init__.py
xlranker/bio/pairs.py
xlranker/bio/peptide.py
xlranker/bio/protein.py
xlranker/data/__init__.py
xlranker/data/gmt.pkl.gz
xlranker/data/ppi.parquet
xlranker/data/uniprot_5_22.fa.tar.xz
xlranker/ml/__init__.py
xlranker/ml/models.py
xlranker/parsimony/__init__.py
xlranker/parsimony/prioritize.py
xlranker/util/__init__.py
xlranker/util/mapping.py
xlranker/util/readers.py
xlranker-0.2.1.dist-info/METADATA
xlranker-0.2.1.dist-info/WHEEL
xlranker-0.2.1.dist-info/entry_points.txt
xlranker-0.2.1.dist-info/licenses/LICENSE
xlranker-0.2.1.dist-info/RECORD
