Metadata-Version: 2.4
Name: xlranker
Version: 0.2.1
Summary: PPI-XL Ranking Tool
License-Expression: MIT
License-File: LICENSE
Requires-Python: >=3.10
Requires-Dist: biopython>=1.85
Requires-Dist: cyclopts>=3.15.0
Requires-Dist: networkx>=3.4.2
Requires-Dist: polars>=1.29.0
Requires-Dist: questionary>=2.1.0
Requires-Dist: scikit-learn>=1.6.1
Requires-Dist: xgboost>=3.0.0
